rubika_bot/__init__.py
rubika_bot/exceptions.py
rubika_bot/models.py
rubika_bot/requests.py
rubika_bot-1.0.19.dist-info/LICENSE
rubika_bot-1.0.19.dist-info/METADATA
rubika_bot-1.0.19.dist-info/WHEEL
rubika_bot-1.0.19.dist-info/top_level.txt
rubika_bot-1.0.19.dist-info/RECORD
