Metadata-Version: 2.1
Name: rubika-bot
Version: 1.0.19
Summary: Rubika Bot Library
Home-page: https://github.com/alirn76/rubika-bot
Author: Rubika Team
Author-email: AliRn76@yahoo.com
License: MIT
Keywords: rubika,bot,rubika-bot
Classifier: License :: OSI Approved :: MIT License
Classifier: Operating System :: OS Independent
Classifier: Programming Language :: Python :: 3.8
Classifier: Programming Language :: Python :: 3.9
Classifier: Programming Language :: Python :: 3.10
Requires-Python: >=3.8
License-File: LICENSE
Requires-Dist: requests
Requires-Dist: pydantic
